MANIFEST.in
README.rst
setup.py
ogp/__init__.py
ogp/opengraph.py
ogp/test.py
ogp.egg-info/PKG-INFO
ogp.egg-info/SOURCES.txt
ogp.egg-info/dependency_links.txt
ogp.egg-info/requires.txt
ogp.egg-info/top_level.txt