Metadata-Version: 1.1
Name: ogp
Version: 0.8
Summary: A module to parse the Open Graph Protocol
Home-page: https://github.com/graingert/opengraph
Author: Erik Rivera
Author-email: erik.river@gmail.com
License: MIT
Keywords: opengraph protocol facebook
Platform: UNKNOWN
Classifier: Development Status :: 3 - Alpha
Classifier: Intended Audience :: Developers
Classifier: Programming Language :: Python
Classifier: Topic :: Text Processing :: Markup :: HTML
Classifier: Topic :: Software Development :: Libraries :: Python Modules
